suparkanbun/__init__.py
suparkanbun/download.py
suparkanbun/simplify.py
suparkanbun/suparkanbun.py
suparkanbun/tradify.py
suparkanbun/models/gloss.orig.txt
suparkanbun/models/labelPOS.txt
suparkanbun/models/guwenbert-base.danku/config.json
suparkanbun/models/guwenbert-base.danku/filesize.txt
suparkanbun/models/guwenbert-base.danku/special_tokens_map.json
suparkanbun/models/guwenbert-base.danku/tokenizer_config.json
suparkanbun/models/guwenbert-base.danku/vocab.txt
suparkanbun/models/guwenbert-base.pos/config.json
suparkanbun/models/guwenbert-base.pos/filesize.txt
suparkanbun/models/guwenbert-base.pos/special_tokens_map.json
suparkanbun/models/guwenbert-base.pos/tokenizer_config.json
suparkanbun/models/guwenbert-base.pos/vocab.txt
suparkanbun/models/guwenbert-large.danku/config.json
suparkanbun/models/guwenbert-large.danku/filesize.txt
suparkanbun/models/guwenbert-large.danku/special_tokens_map.json
suparkanbun/models/guwenbert-large.danku/tokenizer_config.json
suparkanbun/models/guwenbert-large.danku/vocab.txt
suparkanbun/models/guwenbert-large.pos/config.json
suparkanbun/models/guwenbert-large.pos/filesize.txt
suparkanbun/models/guwenbert-large.pos/special_tokens_map.json
suparkanbun/models/guwenbert-large.pos/tokenizer_config.json
suparkanbun/models/guwenbert-large.pos/vocab.txt
suparkanbun/models/roberta-classical-chinese-base-char.danku/config.json
suparkanbun/models/roberta-classical-chinese-base-char.danku/filesize.txt
suparkanbun/models/roberta-classical-chinese-base-char.danku/special_tokens_map.json
suparkanbun/models/roberta-classical-chinese-base-char.danku/tokenizer_config.json
suparkanbun/models/roberta-classical-chinese-base-char.danku/vocab.txt
suparkanbun/models/roberta-classical-chinese-base-char.pos/config.json
suparkanbun/models/roberta-classical-chinese-base-char.pos/filesize.txt
suparkanbun/models/roberta-classical-chinese-base-char.pos/special_tokens_map.json
suparkanbun/models/roberta-classical-chinese-base-char.pos/tokenizer_config.json
suparkanbun-1.6.9.dist-info/LICENSE.txt
suparkanbun-1.6.9.dist-info/METADATA
suparkanbun-1.6.9.dist-info/WHEEL
suparkanbun-1.6.9.dist-info/top_level.txt
suparkanbun-1.6.9.dist-info/RECORD
