Metadata-Version: 2.1
Name: suparkanbun
Version: 1.6.9
Summary: Tokenizer POS-tagger and Dependency-parser for Classical Chinese
Home-page: https://github.com/KoichiYasuoka/SuPar-Kanbun
Author: Koichi Yasuoka
Author-email: yasuoka@kanji.zinbun.kyoto-u.ac.jp
License: MIT
Project-URL: Source, https://github.com/KoichiYasuoka/SuPar-Kanbun
Project-URL: Tracker, https://github.com/KoichiYasuoka/SuPar-Kanbun/issues
Keywords: NLP Chinese
Classifier: License :: OSI Approved :: MIT License
Classifier: Programming Language :: Python :: 3
Classifier: Operating System :: OS Independent
Classifier: Topic :: Text Processing :: Linguistic
Requires-Python: >=3.7
License-File: LICENSE.txt
Requires-Dist: esupar (>=1.8.8)
Requires-Dist: spacy (>=2.2.2)
